{
  "msg" : "SUCCESS",
  "result" : true,
  "data" : {
    "totalSize" : 98,
    "list" : [ {
      "name" : "买入交易",
      "list" : [ {
        "symbol" : "BTCUSDT",
        "amount" : "0.01",
        "field-cash-amount" : "84.500000000000000000",
        "fieldFees" : "0.00002",
        "account-id" : "1033900",
        "source" : "margin-app",
        "type" : "buy-limit",
        "finished-at" : 1521961976032,
        "finishedAt" : "2018-03-25 15:12:56",
        "createdAt" : "2018-03-25 07:58:30",
        "accountId" : "1033900",
        "total" : 84.5,
        "canceledAt" : "1970-01-01 08:00:00",
        "price" : "8450",
        "fieldCashAmount" : "84.5",
        "canceled-at" : 0,
        "fieldAmount" : "0.01",
        "created-at" : 1521935910742,
        "field-fees" : "0.000020000000000000",
        "id" : 2693011404,
        "state" : "filled",
        "field-amount" : "0.010000000000000000"
      }, {
        "symbol" : "BTCUSDT",
        "amount" : "0.01",
        "field-cash-amount" : "86.000000000000000000",
        "fieldFees" : "0.00002",
        "account-id" : "1033900",
        "source" : "margin-app",
        "type" : "buy-limit",
        "finished-at" : 1521935687857,
        "finishedAt" : "2018-03-25 07:54:47",
        "createdAt" : "2018-03-25 07:52:17",
        "accountId" : "1033900",
        "total" : 86.0,
        "canceledAt" : "1970-01-01 08:00:00",
        "price" : "8600",
        "fieldCashAmount" : "86",
        "canceled-at" : 0,
        "fieldAmount" : "0.01",
        "created-at" : 1521935537393,
        "field-fees" : "0.000020000000000000",
        "id" : 2692841574,
        "state" : "filled",
        "field-amount" : "0.010000000000000000"
      }, {
        "symbol" : "BTCUSDT",
        "amount" : "0.01",
        "field-cash-amount" : "0.0",
        "fieldFees" : "0",
        "account-id" : "1033900",
        "source" : "margin-app",
        "type" : "buy-limit",
        "finished-at" : 1521771893246,
        "finishedAt" : "2018-03-23 10:24:53",
        "createdAt" : "2018-03-22 22:38:46",
        "accountId" : "1033900",
        "total" : 84.0,
        "canceledAt" : "2018-03-23 10:24:53",
        "price" : "8400",
        "fieldCashAmount" : "0",
        "canceled-at" : 1521771893062,
        "fieldAmount" : "0",
        "created-at" : 1521729526666,
        "field-fees" : "0.0",
        "id" : 2608204807,
        "state" : "canceled",
        "field-amount" : "0.0"
      }, {
        "symbol" : "BTCUSDT",
        "amount" : "0.02",
        "field-cash-amount" : "150.000000000000000000",
        "fieldFees" : "0.00004",
        "account-id" : "1033900",
        "source" : "margin-app",
        "type" : "buy-limit",
        "finished-at" : 1521382057717,
        "finishedAt" : "2018-03-18 22:07:37",
        "createdAt" : "2018-03-15 23:33:15",
        "accountId" : "1033900",
        "total" : 150.0,
        "canceledAt" : "1970-01-01 08:00:00",
        "price" : "7500",
        "fieldCashAmount" : "150",
        "canceled-at" : 0,
        "fieldAmount" : "0.02",
        "created-at" : 1521127995628,
        "field-fees" : "0.000040000000000000",
        "id" : 2373512053,
        "state" : "filled",
        "field-amount" : "0.020000000000000000"
      }, {
        "symbol" : "BTCUSDT",
        "amount" : "0.02",
        "field-cash-amount" : "174.000000000000000000",
        "fieldFees" : "0.00004",
        "account-id" : "1033900",
        "source" : "margin-app",
        "type" : "buy-limit",
        "finished-at" : 1521024360726,
        "finishedAt" : "2018-03-14 18:46:00",
        "createdAt" : "2018-03-14 18:44:01",
        "accountId" : "1033900",
        "total" : 174.0,
        "canceledAt" : "1970-01-01 08:00:00",
        "price" : "8700",
        "fieldCashAmount" : "174",
        "canceled-at" : 0,
        "fieldAmount" : "0.02",
        "created-at" : 1521024241838,
        "field-fees" : "0.000040000000000000",
        "id" : 2328202944,
        "state" : "filled",
        "field-amount" : "0.020000000000000000"
      }, {
        "symbol" : "BTCUSDT",
        "amount" : "0.03",
        "field-cash-amount" : "0.0",
        "fieldFees" : "0",
        "account-id" : "1033900",
        "source" : "margin-app",
        "type" : "buy-limit",
        "finished-at" : 1521126978034,
        "finishedAt" : "2018-03-15 23:16:18",
        "createdAt" : "2018-03-12 23:43:43",
        "accountId" : "1033900",
        "total" : 225.0,
        "canceledAt" : "2018-03-15 23:16:17",
        "price" : "7500",
        "fieldCashAmount" : "0",
        "canceled-at" : 1521126977950,
        "fieldAmount" : "0",
        "created-at" : 1520869423197,
        "field-fees" : "0.0",
        "id" : 2269390107,
        "state" : "canceled",
        "field-amount" : "0.0"
      }, {
        "symbol" : "BTCUSDT",
        "amount" : "0.03",
        "field-cash-amount" : "241.200000000000000000",
        "fieldFees" : "0.00006",
        "account-id" : "1033900",
        "source" : "margin-app",
        "type" : "buy-limit",
        "finished-at" : 1521063957931,
        "finishedAt" : "2018-03-15 05:45:57",
        "createdAt" : "2018-03-11 09:23:55",
        "accountId" : "1033900",
        "total" : 241.2,
        "canceledAt" : "1970-01-01 08:00:00",
        "price" : "8040",
        "fieldCashAmount" : "241.2",
        "canceled-at" : 0,
        "fieldAmount" : "0.03",
        "created-at" : 1520731435457,
        "field-fees" : "0.000060000000000000",
        "id" : 2217944562,
        "state" : "filled",
        "field-amount" : "0.030000000000000000"
      }, {
        "symbol" : "BTCUSDT",
        "amount" : "0.02",
        "field-cash-amount" : "0.0",
        "fieldFees" : "0",
        "account-id" : "1033900",
        "source" : "margin-app",
        "type" : "buy-limit",
        "finished-at" : 1520869400967,
        "finishedAt" : "2018-03-12 23:43:20",
        "createdAt" : "2018-03-11 09:23:42",
        "accountId" : "1033900",
        "total" : 169.0,
        "canceledAt" : "2018-03-12 23:43:20",
        "price" : "8450",
        "fieldCashAmount" : "0",
        "canceled-at" : 1520869400911,
        "fieldAmount" : "0",
        "created-at" : 1520731422733,
        "field-fees" : "0.0",
        "id" : 2217939583,
        "state" : "canceled",
        "field-amount" : "0.0"
      }, {
        "symbol" : "BTCUSDT",
        "amount" : "0.03",
        "field-cash-amount" : "271.500000000000000000",
        "fieldFees" : "0.00006",
        "account-id" : "1033900",
        "source" : "margin-app",
        "type" : "buy-limit",
        "finished-at" : 1520705389889,
        "finishedAt" : "2018-03-11 02:09:49",
        "createdAt" : "2018-03-10 20:00:55",
        "accountId" : "1033900",
        "total" : 271.5,
        "canceledAt" : "1970-01-01 08:00:00",
        "price" : "9050",
        "fieldCashAmount" : "271.5",
        "canceled-at" : 0,
        "fieldAmount" : "0.03",
        "created-at" : 1520683255843,
        "field-fees" : "0.000060000000000000",
        "id" : 2199343065,
        "state" : "filled",
        "field-amount" : "0.030000000000000000"
      }, {
        "symbol" : "BTCUSDT",
        "amount" : "0.0813",
        "field-cash-amount" : "715.440000000000000000",
        "fieldFees" : "0.000162",
        "account-id" : "1033900",
        "source" : "margin-web",
        "type" : "buy-limit",
        "finished-at" : 1520715756573,
        "finishedAt" : "2018-03-11 05:02:36",
        "createdAt" : "2018-03-10 19:18:07",
        "accountId" : "1033900",
        "total" : 715.4399999999999,
        "canceledAt" : "1970-01-01 08:00:00",
        "price" : "8800",
        "fieldCashAmount" : "715.44",
        "canceled-at" : 0,
        "fieldAmount" : "0.0813",
        "created-at" : 1520680687802,
        "field-fees" : "0.000162600000000000",
        "id" : 2198387808,
        "state" : "filled",
        "field-amount" : "0.081300000000000000"
      } ]
    }, {
      "name" : "卖出交易",
      "list" : [ {
        "symbol" : "BTCUSDT",
        "amount" : "0.0187",
        "field-cash-amount" : "0.0",
        "fieldFees" : "0",
        "account-id" : "1033900",
        "source" : "margin-app",
        "type" : "sell-limit",
        "finished-at" : 1520680781325,
        "finishedAt" : "2018-03-10 19:19:41",
        "createdAt" : "2018-03-09 09:48:04",
        "accountId" : "1033900",
        "total" : 183.260,
        "canceledAt" : "2018-03-10 19:19:41",
        "price" : "9800",
        "fieldCashAmount" : "0",
        "canceled-at" : 1520680781241,
        "fieldAmount" : "0",
        "created-at" : 1520560084289,
        "field-fees" : "0.0",
        "id" : 2150641739,
        "state" : "canceled",
        "field-amount" : "0.0"
      }, {
        "symbol" : "ITCUSDT",
        "amount" : "99.8",
        "field-cash-amount" : "0.0",
        "fieldFees" : "0",
        "account-id" : "463593",
        "source" : "spot-app",
        "type" : "sell-limit",
        "finished-at" : 1520869544399,
        "finishedAt" : "2018-03-12 23:45:44",
        "createdAt" : "2018-03-04 00:22:51",
        "accountId" : "463593",
        "total" : 209.58,
        "canceledAt" : "2018-03-12 23:45:44",
        "price" : "2.1",
        "fieldCashAmount" : "0",
        "canceled-at" : 1520869544254,
        "fieldAmount" : "0",
        "created-at" : 1520094171694,
        "field-fees" : "0.0",
        "id" : 1999712536,
        "state" : "canceled",
        "field-amount" : "0.0"
      }, {
        "symbol" : "ITCUSDT",
        "amount" : "99.8",
        "field-cash-amount" : "201.845500000000000000",
        "fieldFees" : "0.403691",
        "account-id" : "463593",
        "source" : "spot-app",
        "type" : "sell-limit",
        "finished-at" : 1520093965755,
        "finishedAt" : "2018-03-04 00:19:25",
        "createdAt" : "2018-03-04 00:19:24",
        "accountId" : "463593",
        "total" : 201.8455,
        "canceledAt" : "1970-01-01 08:00:00",
        "price" : "2.0225",
        "fieldCashAmount" : "201.8455",
        "canceled-at" : 0,
        "fieldAmount" : "99.8",
        "created-at" : 1520093964046,
        "field-fees" : "0.403691000000000000",
        "id" : 1999647330,
        "state" : "filled",
        "field-amount" : "99.800000000000000000"
      }, {
        "symbol" : "ITCUSDT",
        "amount" : "99.8",
        "field-cash-amount" : "0.0",
        "fieldFees" : "0",
        "account-id" : "463593",
        "source" : "web",
        "type" : "sell-limit",
        "finished-at" : 1520089725379,
        "finishedAt" : "2018-03-03 23:08:45",
        "createdAt" : "2018-03-03 11:10:52",
        "accountId" : "463593",
        "total" : 201.596,
        "canceledAt" : "2018-03-03 23:08:45",
        "price" : "2.02",
        "fieldCashAmount" : "0",
        "canceled-at" : 1520089725179,
        "fieldAmount" : "0",
        "created-at" : 1520046652338,
        "field-fees" : "0.0",
        "id" : 1985186619,
        "state" : "canceled",
        "field-amount" : "0.0"
      }, {
        "symbol" : "ITCUSDT",
        "amount" : "99.8",
        "field-cash-amount" : "0.0",
        "fieldFees" : "0",
        "account-id" : "463593",
        "source" : "spot-app",
        "type" : "sell-limit",
        "finished-at" : 1520046617726,
        "finishedAt" : "2018-03-03 11:10:17",
        "createdAt" : "2018-03-01 08:25:47",
        "accountId" : "463593",
        "total" : 249.5,
        "canceledAt" : "2018-03-03 11:10:17",
        "price" : "2.5",
        "fieldCashAmount" : "0",
        "canceled-at" : 1520046617665,
        "fieldAmount" : "0",
        "created-at" : 1519863947415,
        "field-fees" : "0.0",
        "id" : 1929110471,
        "state" : "canceled",
        "field-amount" : "0.0"
      }, {
        "symbol" : "BTCUSDT",
        "amount" : "0.05",
        "field-cash-amount" : "505.759000000000000000",
        "fieldFees" : "1.011518",
        "account-id" : "1033900",
        "source" : "margin-app",
        "type" : "sell-market",
        "finished-at" : 1519651714720,
        "finishedAt" : "2018-02-26 21:28:34",
        "createdAt" : "2018-02-26 21:28:34",
        "accountId" : "1033900",
        "total" : 0.0,
        "canceledAt" : "1970-01-01 08:00:00",
        "price" : "0",
        "fieldCashAmount" : "505.759",
        "canceled-at" : 0,
        "fieldAmount" : "0.05",
        "created-at" : 1519651714196,
        "field-fees" : "1.011518000000000000",
        "id" : 1855519038,
        "state" : "filled",
        "field-amount" : "0.050000000000000000"
      }, {
        "symbol" : "BTCUSDT",
        "amount" : "0.05",
        "field-cash-amount" : "0.0",
        "fieldFees" : "0",
        "account-id" : "1033900",
        "source" : "margin-app",
        "type" : "sell-limit",
        "finished-at" : 1519651705059,
        "finishedAt" : "2018-02-26 21:28:25",
        "createdAt" : "2018-02-26 21:27:52",
        "accountId" : "1033900",
        "total" : 506.551,
        "canceledAt" : "2018-02-26 21:28:24",
        "price" : "10131.02",
        "fieldCashAmount" : "0",
        "canceled-at" : 1519651704799,
        "fieldAmount" : "0",
        "created-at" : 1519651672420,
        "field-fees" : "0.0",
        "id" : 1855505121,
        "state" : "canceled",
        "field-amount" : "0.0"
      }, {
        "symbol" : "BTCUSDT",
        "amount" : "0.05",
        "field-cash-amount" : "485.967000000000000000",
        "fieldFees" : "0.971934",
        "account-id" : "1033900",
        "source" : "margin-app",
        "type" : "sell-market",
        "finished-at" : 1519624984252,
        "finishedAt" : "2018-02-26 14:03:04",
        "createdAt" : "2018-02-26 10:42:19",
        "accountId" : "1033900",
        "total" : 0.0,
        "canceledAt" : "1970-01-01 08:00:00",
        "price" : "0",
        "fieldCashAmount" : "485.967",
        "canceled-at" : 0,
        "fieldAmount" : "0.05",
        "created-at" : 1519612939952,
        "field-fees" : "0.971934000000000000",
        "id" : 1844905443,
        "state" : "filled",
        "field-amount" : "0.050000000000000000"
      }, {
        "symbol" : "BTCUSDT",
        "amount" : "0.06",
        "field-cash-amount" : "582.000000000000000000",
        "fieldFees" : "1.163999",
        "account-id" : "1033900",
        "source" : "margin-web",
        "type" : "sell-limit",
        "finished-at" : 1519610258231,
        "finishedAt" : "2018-02-26 09:57:38",
        "createdAt" : "2018-02-25 21:39:19",
        "accountId" : "1033900",
        "total" : 582.0,
        "canceledAt" : "1970-01-01 08:00:00",
        "price" : "9700",
        "fieldCashAmount" : "582",
        "canceled-at" : 0,
        "fieldAmount" : "0.06",
        "created-at" : 1519565959863,
        "field-fees" : "1.163999999999999999",
        "id" : 1828458513,
        "state" : "filled",
        "field-amount" : "0.060000000000000000"
      }, {
        "symbol" : "BTCUSDT",
        "amount" : "0.02",
        "field-cash-amount" : "0.0",
        "fieldFees" : "0",
        "account-id" : "1033900",
        "source" : "margin-web",
        "type" : "sell-limit",
        "finished-at" : 1519565925765,
        "finishedAt" : "2018-02-25 21:38:45",
        "createdAt" : "2018-02-25 21:35:05",
        "accountId" : "1033900",
        "total" : 194.0,
        "canceledAt" : "2018-02-25 21:38:45",
        "price" : "9700",
        "fieldCashAmount" : "0",
        "canceled-at" : 1519565925644,
        "fieldAmount" : "0",
        "created-at" : 1519565705008,
        "field-fees" : "0.0",
        "id" : 1828358535,
        "state" : "canceled",
        "field-amount" : "0.0"
      } ]
    } ]
  },
  "status" : "SUCCESS"
}